appoptics_metrics/__init__.py
appoptics_metrics/aggregator.py
appoptics_metrics/alerts.py
appoptics_metrics/annotations.py
appoptics_metrics/exceptions.py
appoptics_metrics/metrics.py
appoptics_metrics/queue.py
appoptics_metrics/spaces.py
appoptics_metrics/streams.py
appoptics_metrics-5.1.0.dist-info/METADATA
appoptics_metrics-5.1.0.dist-info/RECORD
appoptics_metrics-5.1.0.dist-info/WHEEL
appoptics_metrics-5.1.0.dist-info/top_level.txt
