Metadata-Version: 2.1
Name: appoptics-metrics
Version: 5.1.0
Summary: Python API Wrapper for AppOptics Metrics
Home-page: https://github.com/appoptics/appoptics-api-python
Author: AppOptics
Author-email: support@appoptics.com
License: https://github.com/appoptics/appoptics-api-python/blob/master/LICENSE
Platform: Posix; MacOS X; Windows
Classifier: Development Status :: 3 - Alpha
Classifier: Intended Audience :: Developers
Classifier: License :: OSI Approved :: MIT License
Classifier: Operating System :: OS Independent
Classifier: Topic :: Internet
Classifier: Programming Language :: Python
Classifier: Programming Language :: Python :: 3
Requires-Dist: six
